{"rows":10,"os":"0","page":"1","total":"1","projects":{"P001702":{"id":"P001702","projectfinancialtype":"IDA","regionname":"Africa","prodline":"PE","lendinginstr":"Specific Investment Loan","lendinginstrtype":"IN","supplementprojectflg":"N","productlinetype":"L","projectstatusdisplay":"Closed","status":"Closed","project_name":"Forestry Project","board_approval_month":"March","approvalfy":"1979","boardapprovaldate":"1979-03-06T00:00:00Z","closingdate":"1985-06-30T00:00:00Z","lendprojectcost":"4,500,000","ibrdcommamt":"0","idacommamt":"4,500,000","totalamt":"4,500,000","grantamt":"0","url":"http://www.worldbank.org/projects/P001702/forestry-project?lang=en","countryshortname":"Mali","prodlinetext":"IBRD/IDA","keywords":{"cdata":"afforestation,agricultural output,agriculture,arable land,Audits,charcoal,Climate,conservation,crop production,crops,cultivation,destumping,disequilibrium,drought,dry spell,dry weather,Economic Analysis,erosion,Eucalyptus,Expenditures,felling,fires,fish,Fisheries,fishing,fodder,forest,forest areas,forest cover,Forest Management,Forest Nurseries,Forest Plantations,forest products,forest protection,forest regrowth,Forest Reserves,forest services,Forestry,forestry activities,Forestry Department,forestry development,Forestry education,Forestry Management,forestry operations,Forestry Project,Forestry research,forestry sector,Forestry Subsector,forestry training,fruit,fruits,fuelwood,groundwater,gum arabic,hunting,imports,Income,logging,National Forestry,natural forests,natural regeneration,oil,parks,plantation,planting,poles,population densities,population growth,population pressures,rainfall,rainfall conditions,rainfall volume,reservoir,roundwood,rural areas,Soils,Teak,Topography,tree plantations,tree planting,trees,unemployment,vegetation,wildlife,wood,wood lots,wood product,Wood Production,wood products,wood sales,Wood Trade,woodlots"},"project_abstract":{"cdata":"The project would support a five-year program aimed at increasing fuelwood and building pole supplies especially for urban areas, and at strengthening the Forestry Department of the Ministry of Rural Development. The project would (a) establish 3,400 ha of industrial rainfed tree plantations near Bamako; (b) establish on a trial basis 60 ha of rainfed tree plantations near Segou and 70 ha of partially irrigated tree plantations near Mopti; (c) apply modern forest management techniques on a trial basis; (d) establish three rural forestry nurseries and rehabilitate an existing one; and (e) execute studies to investigate more efficient wood uses, to examine possibilities to set up rural forestry activities that would generate participation by the local population and to examine the scope of the follow-up project."},"country_namecode":"Republic of Mali!$!ML","sector1":{"Name":"Forestry","Percent":100},"theme1":{"Name":"","Percent":0},"totalcommamt":"4,500,000","sector":[{"Name":"Forestry"}],"docty":"Project Performance Assessment Report,Agreement,Memorandum & Recommendation of the President,Staff Appraisal Report","countrycode":"ML","sectorcode":"AT","mjsector_namecode":[{"name":"Agriculture, fishing, and forestry","code":"AX"}],"mjthemecode":"10","mjtheme_namecode":[{"name":"","code":"10"}],"sector_namecode":[{"name":"Forestry","code":"AT"}],"source":"IBRD","majorsector_percent":[{"Name":"Agriculture, fishing, and forestry","Percent":100}],"projectdocs":[{"DocTypeDesc":"Project Performance Assessment Report (PPAR),  Vol.1","DocType":"PPAR","EntityID":"000009265_3960924180656","DocURL":"http://www-wds.worldbank.org/servlet/WDSServlet?pcont=details&eid=000009265_3960924180656","DocDate":"30-JUN-1989"},{"DocTypeDesc":"Agreement (AGR),  Vol.","DocType":"AGR","EntityID":"090224b082228c55_1_0","DocURL":"http://www-wds.worldbank.org/servlet/WDSServlet?pcont=details&eid=090224b082228c55_1_0","DocDate":"06-MAR-1979"},{"DocTypeDesc":"Memorandum & Recommendation of the President (MOP),  Vol.1","DocType":"MOP","EntityID":"000178830_98101902321942","DocURL":"http://www-wds.worldbank.org/servlet/WDSServlet?pcont=details&eid=000178830_98101902321942","DocDate":"28-FEB-1979"},{"DocTypeDesc":"Staff Appraisal Report (SAR),  Vol.1","DocType":"SAR","EntityID":"000178830_98101912410846","DocURL":"http://www-wds.worldbank.org/servlet/WDSServlet?pcont=details&eid=000178830_98101912410846","DocDate":"31-JAN-1979"}],"countryname":"Republic of Mali"}},"facets":{}}