{"rows":10,"os":"0","page":"1","total":"1","projects":{"P003826":{"id":"P003826","projectfinancialtype":"IBRD","regionname":"East Asia and Pacific","prodline":"PE","lendinginstr":"Specific Investment Loan","lendinginstrtype":"IN","supplementprojectflg":"N","productlinetype":"L","projectstatusdisplay":"Closed","status":"Closed","project_name":"Power Project (13)","board_approval_month":"June","approvalfy":"1983","boardapprovaldate":"1983-06-02T00:00:00Z","closingdate":"1990-12-31T00:00:00Z","lendprojectcost":"279,000,000","ibrdcommamt":"279,000,000","idacommamt":"0","totalamt":"279,000,000","grantamt":"0","url":"http://www.worldbank.org/projects/P003826/power-project-13?lang=en","countryshortname":"Indonesia","prodlinetext":"IBRD/IDA","keywords":{"cdata":"abundant energy,access to electricity,access to electricity supply,availability of gas,barrels of oil,beneficial impact,Benefit Streams,biomass production,bituminous coal,brown coal,Coal,coal mining,coal production,coal reserves,coal resources,commercial energy,commercial energy consumption,commercial fuels,conservation,conservation measures,Construction,covers,Dam Safety,deforestation,demand for electricity,demand forecast,demand growth,distribution losses,domestic coal,drilling,Ecology,economic problems,economies of scale,Electric Power,electrical energy,Electricity,electricity demand,electricity generation,electricity supply,Energy Consumption,energy development,Energy Generation,energy planning,energy policies,energy policy,energy prices,energy problems,Energy Production,energy products,Energy Resources,Energy Sector,energy sources,energy subsidies,energy technologies,energy usage,Engineers,Environmental Aspects,Expenditures,exploitation,financial resources,Fuel,Fuel Consumption,fuelwood,Geothermal Energy,grid,heat,heating,Hydraulic Engineering,Hydro resources,hydroelectric power,Hydrology,Income,Insurance,Irrigation,kerosene,Legislation,lignite,Marginal Cost,marginal costs,Mines,Natural Gas,natural gas resources,natural gas sector,Nuclear Power,nuclear power stations,Oil,Oil Company,oil consumption,oil development,oil imports,oil price,oil prices,oil production,oil sector,petroleum,petroleum products,pipeline,pipeline system,pipelines,power generation,power markets,power"},"project_abstract":{"cdata":"The Thirteenth Power Project will provide peak hydroelectric generating capacity to complement the steady growth of base-load coal-fired thermal generating capacity on the Java grid from 1984 onwards. The project comprises: (a) construction of a storage dam, 125 m high, at Cirata on the Citarum river; a 1 km water conductor system comprising tunnels, surgetanks, and penstock tunnels; and a 500 MW power station (with four generating sets each rated at 125 MW), with an associated 500 kV step-up substation and a 25 km transmission line to nearby Saguling; (b) construction machinery for a PLN task force; and (c) support of the GOI's energy sector program by providing technical assistance, studies and related equipment."},"country_namecode":"Republic of Indonesia!$!ID","sector1":{"Name":"(Historic)Hydro","Percent":100},"theme1":{"Name":"","Percent":0},"totalcommamt":"279,000,000","sector":[{"Name":"(Historic)Hydro"}],"docty":"Project Agreement,Loan Agreement,Memorandum & Recommendation of the President,Staff Appraisal Report","countrycode":"ID","sectorcode":"PH","mjsector_namecode":[{"name":"(Historic)Electric Power & Other Energy","code":"PX"}],"mjthemecode":"9","mjtheme_namecode":[{"name":"","code":"9"}],"sector_namecode":[{"name":"(Historic)Hydro","code":"PH"}],"source":"IBRD","majorsector_percent":[{"Name":"","Percent":0}],"projectdocs":[{"DocTypeDesc":"Project Agreement (PRA),  Vol.","DocType":"PRA","EntityID":"090224b081e9998e_1_0","DocURL":"http://www-wds.worldbank.org/servlet/WDSServlet?pcont=details&eid=090224b081e9998e_1_0","DocDate":"02-JUN-1983"},{"DocTypeDesc":"Loan Agreement (LA),  Vol.","DocType":"LA","EntityID":"090224b081e9998c_1_0","DocURL":"http://www-wds.worldbank.org/servlet/WDSServlet?pcont=details&eid=090224b081e9998c_1_0","DocDate":"02-JUN-1983"},{"DocTypeDesc":"Memorandum & Recommendation of the President (MOP),  Vol.1","DocType":"MOP","EntityID":"000178830_98101902422163","DocURL":"http://www-wds.worldbank.org/servlet/WDSServlet?pcont=details&eid=000178830_98101902422163","DocDate":"31-MAY-1983"},{"DocTypeDesc":"Staff Appraisal Report (SAR),  Vol.1","DocType":"SAR","EntityID":"000178830_98101901020421","DocURL":"http://www-wds.worldbank.org/servlet/WDSServlet?pcont=details&eid=000178830_98101901020421","DocDate":"31-MAY-1983"}],"countryname":"Republic of Indonesia"}},"facets":{}}