{"rows":10,"os":"0","page":"1","total":"1","projects":{"P003037":{"id":"P003037","projectfinancialtype":"IDA","regionname":"Africa","prodline":"PE","lendinginstr":"Specific Investment Loan","lendinginstrtype":"IN","supplementprojectflg":"N","productlinetype":"L","projectstatusdisplay":"Closed","status":"Closed","project_name":"Office National des Transports Modernization Project (02)","board_approval_month":"October","approvalfy":"1982","boardapprovaldate":"1981-10-06T00:00:00Z","closingdate":"1990-03-31T00:00:00Z","lendprojectcost":"26,000,000","ibrdcommamt":"0","idacommamt":"26,000,000","totalamt":"26,000,000","grantamt":"0","url":"http://www.worldbank.org/projects/P003037/office-national-des-transports-modernization-project-02?lang=en","countryshortname":"Congo, Democratic Republic of","prodlinetext":"IBRD/IDA","country_namecode":"Democratic Republic of the Congo!$!ZR","sector1":{"Name":"Ports, waterways and shipping","Percent":100},"theme1":{"Name":"","Percent":0},"totalcommamt":"26,000,000","sector":[{"Name":"Ports, waterways and shipping"}],"docty":"Project Agreement,Credit Agreement","countrycode":"ZR","sectorcode":"TP","mjsector_namecode":[{"name":"Transportation","code":"TX"}],"mjthemecode":"7","mjtheme_namecode":[{"name":"","code":"7"}],"sector_namecode":[{"name":"Ports, waterways and shipping","code":"TP"}],"source":"IBRD","majorsector_percent":[{"Name":"Transportation","Percent":100}],"projectdocs":[{"DocTypeDesc":"Project Agreement (PRA),  Vol.","DocType":"PRA","EntityID":"090224b081e0431f_1_0","DocURL":"http://www-wds.worldbank.org/servlet/WDSServlet?pcont=details&eid=090224b081e0431f_1_0","DocDate":"06-OCT-1981"},{"DocTypeDesc":"Credit Agreement (CA),  Vol.","DocType":"CA","EntityID":"090224b081e0431d_1_0","DocURL":"http://www-wds.worldbank.org/servlet/WDSServlet?pcont=details&eid=090224b081e0431d_1_0","DocDate":"06-OCT-1981"}],"countryname":"Democratic Republic of the Congo"}},"facets":{}}