{"rows":10,"os":"0","page":"1","total":"1","projects":{"P008586":{"id":"P008586","projectfinancialtype":"IBRD","regionname":"Europe and Central Asia","prodline":"PE","lendinginstr":"Technical Assistance Loan","lendinginstrtype":"IN","envassesmentcategorycode":"D","supplementprojectflg":"N","productlinetype":"L","projectstatusdisplay":"Closed","status":"Closed","project_name":"Environment Management Project","board_approval_month":"April","approvalfy":"1990","boardapprovaldate":"1990-04-24T00:00:00Z","closingdate":"1996-12-31T00:00:00Z","lendprojectcost":"18,000,000","ibrdcommamt":"18,000,000","idacommamt":"0","totalamt":"18,000,000","grantamt":"0","borrower":"REPUBLIC OF POLAND","impagency":"MINISTRY OF ENVIRON.","url":"http://www.worldbank.org/projects/P008586/environment-management-project?lang=en","countryshortname":"Poland","teamleaderupi":"52119","prodlinetext":"IBRD/IDA","country_namecode":"Republic of Poland!$!PL","sector1":{"Name":"Central government administration","Percent":8},"sector2":{"Name":"Sub-national government administration","Percent":73},"sector3":{"Name":"Other industry","Percent":19},"theme1":{"Name":"Environmental policies and institutions","Percent":33},"theme2":{"Name":"Decentralization","Percent":17},"theme3":{"Name":"Public expenditure, financial management and procurement","Percent":17},"theme4":{"Name":"Pollution management and environmental health","Percent":33},"totalcommamt":"18,000,000","sector":[{"Name":"Central government administration"},{"Name":"Sub-national government administration"},{"Name":"Other industry"}],"docty":"Implementation Completion and Results Report,Loan Agreement,President's Report","countrycode":"PL","sectorcode":"YW,BH,BC","mjsector_namecode":[{"name":"Public Administration, Law, and Justice","code":"BX"},{"name":"Public Administration, Law, and Justice","code":"BX"},{"name":"Industry and trade","code":"YX"}],"mjtheme":["Environment and natural resources management","Public sector governance","Public sector governance","Environment and natural resources management"],"themecode":"84,27,26,82","mjthemecode":"11,2,2,11","mjtheme_namecode":[{"name":"Environment and natural resources management","code":"11"},{"name":"Public sector governance","code":"2"},{"name":"Public sector governance","code":"2"},{"name":"Environment and natural resources management","code":"11"}],"sector_namecode":[{"name":"Central government administration","code":"BC"},{"name":"Sub-national government administration","code":"BH"},{"name":"Other industry","code":"YW"}],"theme_namecode":[{"name":"Environmental policies and institutions","code":"82"},{"name":"Decentralization","code":"26"},{"name":"Public expenditure, financial management and procurement","code":"27"},{"name":"Pollution management and environmental health","code":"84"}],"source":"IBRD","majorsector_percent":[{"Name":"Public Administration, Law, and Justice","Percent":8},{"Name":"Public Administration, Law, and Justice","Percent":73},{"Name":"Industry and trade","Percent":19}],"projectdocs":[{"DocTypeDesc":"Implementation Completion and Results Report (ICR),  Vol.1","DocType":"ICR","EntityID":"000009265_3970909142231","DocURL":"http://www-wds.worldbank.org/servlet/WDSServlet?pcont=details&eid=000009265_3970909142231","DocDate":"30-MAY-1997"},{"DocTypeDesc":"Loan Agreement (LA),  Vol.","DocType":"LA","EntityID":"000114496_2010041616040340","DocURL":"http://www-wds.worldbank.org/servlet/WDSServlet?pcont=details&eid=000114496_2010041616040340","DocDate":"25-APR-1990"},{"DocTypeDesc":"President's Report (PR),  Vol.1","DocType":"PR","EntityID":"000009265_3960929015035","DocURL":"http://www-wds.worldbank.org/servlet/WDSServlet?pcont=details&eid=000009265_3960929015035","DocDate":"02-APR-1990"}],"countryname":"Republic of Poland"}},"facets":{}}