{"rows":10,"os":"0","page":"1","total":"1","projects":{"P008801":{"id":"P008801","projectfinancialtype":"OTHER","regionname":"Europe and Central Asia","prodline":"GE","lendinginstr":"Specific Investment Loan","lendinginstrtype":"IN","envassesmentcategorycode":"C","supplementprojectflg":"N","productlinetype":"L","projectstatusdisplay":"Closed","status":"Closed","project_name":"Biodiversity Conservation GEF Project","board_approval_month":"May","approvalfy":"1996","boardapprovaldate":"1996-05-30T00:00:00Z","closingdate":"2003-09-30T00:00:00Z","lendprojectcost":"26,000,000","ibrdcommamt":"0","idacommamt":"0","totalamt":"0","grantamt":"20,100,000","borrower":"USSIA E","impagency":"IIST","url":"http://www.worldbank.org/projects/P008801/biodiversity-conservation-gef-project?lang=en","countryshortname":"Russian Federation","teamleaderupi":"78122","prodlinetext":"Global Environment Project","country_namecode":"Russian Federation!$!RU","sector1":{"Name":"General agriculture, fishing and forestry sector","Percent":57},"sector2":{"Name":"Central government administration","Percent":23},"sector3":{"Name":"Sub-national government administration","Percent":10},"sector4":{"Name":"Other social services","Percent":10},"theme1":{"Name":"Biodiversity","Percent":23},"theme2":{"Name":"Participation and civic engagement","Percent":22},"theme3":{"Name":"Indigenous peoples","Percent":22},"theme4":{"Name":"Land administration and management","Percent":11},"theme5":{"Name":"Environmental policies and institutions","Percent":22},"totalcommamt":"20,100,000","sector":[{"Name":"General agriculture, fishing and forestry sector"},{"Name":"Central government administration"},{"Name":"Sub-national government administration"},{"Name":"Other social services"}],"docty":"Project Performance Assessment Report,Implementation Completion and Results Report,Grant or Trust Fund Agreement,GEF Project Document","countrycode":"RU","sectorcode":"JB,BH,BC,AZ","mjsector_namecode":[{"name":"Agriculture, fishing, and forestry","code":"AX"},{"name":"Public Administration, Law, and Justice","code":"BX"},{"name":"Public Administration, Law, and Justice","code":"BX"},{"name":"Health and other social services","code":"JX"}],"mjtheme":["Environment and natural resources management","Social dev/gender/inclusion","Social dev/gender/inclusion","Environment and natural resources management","Environment and natural resources management"],"themecode":"82,83,60,57,80","mjthemecode":"11,7,7,11,11","mjtheme_namecode":[{"name":"Environment and natural resources management","code":"11"},{"name":"Social dev/gender/inclusion","code":"7"},{"name":"Social dev/gender/inclusion","code":"7"},{"name":"Environment and natural resources management","code":"11"},{"name":"Environment and natural resources management","code":"11"}],"sector_namecode":[{"name":"General agriculture, fishing and forestry sector","code":"AZ"},{"name":"Central government administration","code":"BC"},{"name":"Sub-national government administration","code":"BH"},{"name":"Other social services","code":"JB"}],"theme_namecode":[{"name":"Biodiversity","code":"80"},{"name":"Participation and civic engagement","code":"57"},{"name":"Indigenous peoples","code":"60"},{"name":"Land administration and management","code":"83"},{"name":"Environmental policies and institutions","code":"82"}],"source":"IBRD","majorsector_percent":[{"Name":"Agriculture, fishing, and forestry","Percent":57},{"Name":"Public Administration, Law, and Justice","Percent":23},{"Name":"Public Administration, Law, and Justice","Percent":10},{"Name":"Health and other social services","Percent":10}],"projectdocs":[{"DocTypeDesc":"Project Performance Assessment Report (PPAR),  Vol.1","DocType":"PPAR","EntityID":"000333038_20080724024840","DocURL":"http://www-wds.worldbank.org/servlet/WDSServlet?pcont=details&eid=000333038_20080724024840","DocDate":"09-MAY-2008"},{"DocTypeDesc":"Implementation Completion and Results Report (ICR),  Vol.1","DocType":"ICR","EntityID":"000012009_20040402124138","DocURL":"http://www-wds.worldbank.org/servlet/WDSServlet?pcont=details&eid=000012009_20040402124138","DocDate":"25-MAR-2004"},{"DocTypeDesc":"Grant or Trust Fund Agreement (GTA),  Vol.","DocType":"GTA","EntityID":"000114496_2010052717130255","DocURL":"http://www-wds.worldbank.org/servlet/WDSServlet?pcont=details&eid=000114496_2010052717130255","DocDate":"29-SEP-1996"},{"DocTypeDesc":"GEF Project Document (PD),  Vol.1","DocType":"PD","EntityID":"000178830_98101911562819","DocURL":"http://www-wds.worldbank.org/servlet/WDSServlet?pcont=details&eid=000178830_98101911562819","DocDate":"31-MAY-1996"}],"countryname":"Russian Federation"}},"facets":{}}