{"rows":10,"os":"0","page":"1","total":"1","projects":{"P010147":{"id":"P010147","projectfinancialtype":"IDA","regionname":"South Asia","prodline":"PE","lendinginstr":"Specific Investment Loan","lendinginstrtype":"IN","supplementprojectflg":"N","productlinetype":"L","projectstatusdisplay":"Closed","status":"Closed","project_name":"Mahakali Irrigation - Stage Project (01)","board_approval_month":"June","approvalfy":"1980","boardapprovaldate":"1980-06-26T00:00:00Z","closingdate":"1988-12-31T00:00:00Z","lendprojectcost":"16,000,000","ibrdcommamt":"0","idacommamt":"16,000,000","totalamt":"16,000,000","grantamt":"0","url":"http://www.worldbank.org/projects/P010147/mahakali-irrigation-stage-project-01?lang=en","countryshortname":"Nepal","prodlinetext":"IBRD/IDA","keywords":{"cdata":"Agricultural Development,Agricultural Extension,agricultural growth,Agricultural Inputs,agricultural land,AGRICULTURAL PRODUCTION,Agricultural Research,Agricultural Training,Agriculture,alluvial soils,aquifer,aquifers,arable land,Benefit Streams,canal irrigation,cash crops,cereals,CIMMYT,commercial banks,concrete pipes,Construction,consumer demand,Cooperatives,cotton,creditworthiness,Crop,crop development,Crop Production,Crop yields,Cropping,Cropping Patterns,cropping systems,crops,cultivable land,Cultivation,Cultivation Practices,discount rates,Drainage,dry season,Economic Analysis,economic conditions,economic development,efficient use,Employment,Equipment,Expenditures,exploitation,extension services,Extension workers,Farm,Farm Incomes,Farm Land,farmer,farmer participation,farmers,farming,farms,feasibility studies,fertilizers,financial resources,food production,food supply,foodgrains,Forest Products,Forestry,Forests,ground level,Groundwater,habitat,HYV,Income,Income Distribution,income levels,Incomes,integration,Interest rates,International Maize and Wheat Improvement Center,irri,irrigated agriculture,Irrigation,irrigation scheme,irrigation systems,irrigation water,jute,labor force,Land Distribution,Land Reform,Land Use,lands,livestock,low rainfall,maize,marketing,Natural Resources,oilseeds,organic matter,paddy,population growth,population pressures,potato,potatoes,poverty incidence,precipitation,Present Value,produce,pulses,Reclamation,Rice,rivers,runoff,Rural Development,s"},"project_abstract":{"cdata":"The proposed project would consist of: (i) improvements to the existing irrigation and drainage system in about 3,400 ha and its extension by another 3,200 ha; (ii) construction of a connected network of all weather access and canal service roads; (iii) construction of buildings for engineering and agricultural activities and staff quarters; (iv) strengthening agricultural extension, research and training activities, including construction of a pilot demonstration farm cum training center; (v) procurement of equipment for construction, survey and laboratory activities and project operation and maintenance; (vi) provision of technical services; (vii) fellowships for Nepali students to study civil and mechanical engineering and agriculture; and (viii) strengthening agricultural development activities in the Bhairawa-Lumbini Groundwater Project (Cr. 654-NEP). The project faces no special risks."},"country_namecode":"Nepal!$!NP","sector1":{"Name":"Irrigation and drainage","Percent":100},"theme1":{"Name":"","Percent":0},"totalcommamt":"16,000,000","sector":[{"Name":"Irrigation and drainage"}],"docty":"Project Completion Report,Memorandum & Recommendation of the President,Staff Appraisal Report,Agreement","countrycode":"NP","sectorcode":"AI","mjsector_namecode":[{"name":"Agriculture, fishing, and forestry","code":"AX"}],"mjthemecode":"11","mjtheme_namecode":[{"name":"","code":"11"}],"sector_namecode":[{"name":"Irrigation and drainage","code":"AI"}],"source":"IBRD","majorsector_percent":[{"Name":"Agriculture, fishing, and forestry","Percent":100}],"projectdocs":[{"DocTypeDesc":"Project Completion Report (PCR),  Vol.1","DocType":"PCR","EntityID":"000009265_3960925042253","DocURL":"http://www-wds.worldbank.org/servlet/WDSServlet?pcont=details&eid=000009265_3960925042253","DocDate":"28-SEP-1990"},{"DocTypeDesc":"Memorandum & Recommendation of the President (MOP),  Vol.1","DocType":"MOP","EntityID":"000178830_98101902355169","DocURL":"http://www-wds.worldbank.org/servlet/WDSServlet?pcont=details&eid=000178830_98101902355169","DocDate":"30-JUN-1980"},{"DocTypeDesc":"Staff Appraisal Report (SAR),  Vol.1","DocType":"SAR","EntityID":"000178830_9810191249424","DocURL":"http://www-wds.worldbank.org/servlet/WDSServlet?pcont=details&eid=000178830_9810191249424","DocDate":"30-JUN-1980"},{"DocTypeDesc":"Agreement (AGR),  Vol.","DocType":"AGR","EntityID":"090224b082228bfc_1_0","DocURL":"http://www-wds.worldbank.org/servlet/WDSServlet?pcont=details&eid=090224b082228bfc_1_0","DocDate":"26-JUN-1980"}],"countryname":"Nepal"}},"facets":{}}