{"rows":10,"os":"0","page":"1","total":"1","projects":{"P010152":{"id":"P010152","projectfinancialtype":"IDA","regionname":"South Asia","prodline":"PE","lendinginstr":"Technical Assistance Loan","lendinginstrtype":"IN","supplementprojectflg":"N","productlinetype":"L","projectstatusdisplay":"Closed","status":"Closed","project_name":"Babai Irrigation Engineering Project","board_approval_month":"January","approvalfy":"1981","boardapprovaldate":"1981-01-06T00:00:00Z","closingdate":"1986-03-31T00:00:00Z","lendprojectcost":"3,500,000","ibrdcommamt":"0","idacommamt":"3,500,000","totalamt":"3,500,000","grantamt":"0","url":"http://www.worldbank.org/projects/P010152/babai-irrigation-engineering-project?lang=en","countryshortname":"Nepal","prodlinetext":"IBRD/IDA","country_namecode":"Nepal!$!NP","sector1":{"Name":"Irrigation and drainage","Percent":100},"theme1":{"Name":"","Percent":0},"totalcommamt":"3,500,000","sector":[{"Name":"Irrigation and drainage"}],"docty":"Project Completion Report,Credit Agreement,President's Report","countrycode":"NP","sectorcode":"AI","mjsector_namecode":[{"name":"Agriculture, fishing, and forestry","code":"AX"}],"mjthemecode":"4","mjtheme_namecode":[{"name":"","code":"4"}],"sector_namecode":[{"name":"Irrigation and drainage","code":"AI"}],"source":"IBRD","majorsector_percent":[{"Name":"Agriculture, fishing, and forestry","Percent":100}],"projectdocs":[{"DocTypeDesc":"Project Completion Report (PCR),  Vol.1","DocType":"PCR","EntityID":"000009265_3960925070259","DocURL":"http://www-wds.worldbank.org/servlet/WDSServlet?pcont=details&eid=000009265_3960925070259","DocDate":"22-MAR-1989"},{"DocTypeDesc":"Credit Agreement (CA),  Vol.","DocType":"CA","EntityID":"090224b081e0453c_1_0","DocURL":"http://www-wds.worldbank.org/servlet/WDSServlet?pcont=details&eid=090224b081e0453c_1_0","DocDate":"06-JAN-1981"},{"DocTypeDesc":"President's Report (PR),  Vol.1","DocType":"PR","EntityID":"000178830_98101902363958","DocURL":"http://www-wds.worldbank.org/servlet/WDSServlet?pcont=details&eid=000178830_98101902363958","DocDate":"31-DEC-1980"}],"countryname":"Nepal"}},"facets":{}}