{"rows":10,"os":"0","page":"1","total":"1","projects":{"P034140":{"id":"P034140","projectfinancialtype":"IBRD","regionname":"Middle East and North Africa","prodline":"PE","lendinginstr":"Specific Investment Loan","lendinginstrtype":"IN","envassesmentcategorycode":"C","supplementprojectflg":"N","productlinetype":"L","projectstatusdisplay":"Closed","status":"Closed","project_name":"Emergency Desert Locust Control Project","board_approval_month":"December","approvalfy":"1994","boardapprovaldate":"1993-12-23T00:00:00Z","closingdate":"1996-06-30T00:00:00Z","lendprojectcost":"51,200,000","ibrdcommamt":"30,000,000","idacommamt":"0","totalamt":"30,000,000","grantamt":"0","borrower":"T A","impagency":"T","url":"http://www.worldbank.org/projects/P034140/emergency-desert-locust-control-project?lang=en","countryshortname":"Algeria","teamleaderupi":"56023","prodlinetext":"IBRD/IDA","country_namecode":"People's Democratic Republic of Algeria!$!DZ","sector1":{"Name":"Agricultural extension and research","Percent":90},"sector2":{"Name":"Central government administration","Percent":10},"theme1":{"Name":"Rural services and infrastructure","Percent":50},"theme2":{"Name":"Natural disaster management","Percent":50},"totalcommamt":"30,000,000","sector":[{"Name":"Agricultural extension and research"},{"Name":"Central government administration"}],"docty":"Implementation Completion and Results Report,Loan Agreement,Loan Agreement,Loan Agreement,President's Report,President's Report","countrycode":"DZ","sectorcode":"BC,AB","mjsector_namecode":[{"name":"Agriculture, fishing, and forestry","code":"AX"},{"name":"Public Administration, Law, and Justice","code":"BX"}],"mjtheme":["Rural development","Social protection and risk management"],"themecode":"52,78","mjthemecode":"10,6","mjtheme_namecode":[{"name":"Rural development","code":"10"},{"name":"Social protection and risk management","code":"6"}],"sector_namecode":[{"name":"Agricultural extension and research","code":"AB"},{"name":"Central government administration","code":"BC"}],"theme_namecode":[{"name":"Rural services and infrastructure","code":"78"},{"name":"Natural disaster management","code":"52"}],"source":"IBRD","majorsector_percent":[{"Name":"Agriculture, fishing, and forestry","Percent":90},{"Name":"Public Administration, Law, and Justice","Percent":10}],"projectdocs":[{"DocTypeDesc":"Implementation Completion and Results Report (ICR),  Vol.1","DocType":"ICR","EntityID":"000009265_3970619110754","DocURL":"http://www-wds.worldbank.org/servlet/WDSServlet?pcont=details&eid=000009265_3970619110754","DocDate":"15-JAN-1997"},{"DocTypeDesc":"Loan Agreement (LA),  Vol.","DocType":"LA","EntityID":"000014464_2010032911505002","DocURL":"http://www-wds.worldbank.org/servlet/WDSServlet?pcont=details&eid=000014464_2010032911505002","DocDate":"27-JAN-1994"},{"DocTypeDesc":"Loan Agreement (),  Vol.","DocType":"000014464_2010032911505002","EntityID":"http://www-wds.worldbank.org/servlet/WDSServlet?pcont=details&eid=000014464_2010032911505002","DocURL":"27-JAN-1994"},{"DocTypeDesc":"Loan Agreement (LA),  Vol.","DocType":"LA","EntityID":"090224b081e99d92_1_0","DocURL":"http://www-wds.worldbank.org/servlet/WDSServlet?pcont=details&eid=090224b081e99d92_1_0","DocDate":"23-DEC-1993"},{"DocTypeDesc":"President's Report (PR),  Vol.1","DocType":"PR","EntityID":"000009265_3961005151957","DocURL":"http://www-wds.worldbank.org/servlet/WDSServlet?pcont=details&eid=000009265_3961005151957","DocDate":"06-DEC-1993"},{"DocTypeDesc":"President's Report (PR),  Vol.2","DocType":"PR","EntityID":"000009265_3961005152000","DocURL":"http://www-wds.worldbank.org/servlet/WDSServlet?pcont=details&eid=000009265_3961005152000","DocDate":"06-DEC-1993"}],"countryname":"People's Democratic Republic of Algeria"}},"facets":{}}