{"rows":10,"os":"0","page":"1","total":"1","projects":{"P070999":{"id":"P070999","projectfinancialtype":"IDA","regionname":"Africa","prodline":"PE","lendinginstr":"Poverty Reduction Support Credit","lendinginstrtype":"AD","envassesmentcategorycode":"C","supplementprojectflg":"N","productlinetype":"L","projectstatusdisplay":"Closed","status":"Closed","project_name":"Poverty Reduction Support Credit I","board_approval_month":"July","approvalfy":"2004","boardapprovaldate":"2004-07-20T00:00:00Z","closingdate":"2005-06-30T00:00:00Z","lendprojectcost":"125,000,000","ibrdcommamt":"0","idacommamt":"125,000,000","totalamt":"125,000,000","grantamt":"0","borrower":"IIST","impagency":"SECETAIA","url":"http://www.worldbank.org/projects/P070999/poverty-reduction-support-credit?lang=en","countryshortname":"Madagascar","teamleaderupi":"20242","prodlinetext":"IBRD/IDA","keywords":{"cdata":"Poverty Reduction"},"project_abstract":{"cdata":"A series of three single tranche Poverty Reduction Support Credits (PRSCs), that will be provided in the form of budget support, is envisaged to support implementation of the Poverty Reduction Strategy Paper (PRSP). PRSC 1 will support the strategic axes of good governance (public expenditure management and anti-corruption), and promoting human development through improved service delivery in education and nutrition. In addition, strengthening monitoring and evaluation will lead to an enhanced accountability and results focus.  PRSC 's support includes assistance to the Government in implementing its 2004 Priority Action Plan for public expenditure management reforms. This includes the preparation and submission to Parliament of the public finance framework law; improved alignment of the 2004 budget to the priorities of the PRSP, the reform of the Treasury, simplification of expenditure management process, the development and submission to Parliament of a new Procurement Code, and strengthening internal controls through the establishment of a General Inspectorate for Finances. PRSC 1 also supports the Government's anti-corruption agenda, including establishment of an operational Anti- Corruption Commission and the development of a national anti-corruption strategy. PRSC 1 also supports Axis 3 on providing human and material security, by supporting the development and implementation of the Government's Education for All Agenda and service delivery in nutrition. Key policy reforms have included an increase in the education budget, measures to decrease education costs for poor households (suppression of school fees, provision of learning materials to all primary students), actions to increase access for poor students (through school construction, salary compensation for teachers paid by parents, teacher recruitment) and reinforcement of management capacity at central and"},"country_namecode":"Republic of Madagascar!$!MG","sector1":{"Name":"General public administration sector","Percent":43},"sector2":{"Name":"General education sector","Percent":28},"sector3":{"Name":"General agriculture, fishing and forestry sector","Percent":13},"sector4":{"Name":"Health","Percent":8},"sector5":{"Name":"General industry and trade sector","Percent":8},"theme1":{"Name":"Public expenditure, financial management and procurement","Percent":29},"theme2":{"Name":"Environmental policies and institutions","Percent":14},"theme3":{"Name":"Rural services and infrastructure","Percent":14},"theme4":{"Name":"Education for all","Percent":29},"theme5":{"Name":"Health system performance","Percent":14},"totalcommamt":"125,000,000","sector":[{"Name":"General public administration sector"},{"Name":"General education sector"},{"Name":"General agriculture, fishing and forestry sector"},{"Name":"Health"},{"Name":"General industry and trade sector"}],"docty":"Implementation Completion and Results Report,Implementation Completion and Results Report,Credit Agreement,Credit Agreement,Program Document,Program Information Document","countrycode":"MG","sectorcode":"YZ,JA,AZ,EZ,BZ","mjsector_namecode":[{"name":"Public Administration, Law, and Justice","code":"BX"},{"name":"Education","code":"EX"},{"name":"Agriculture, fishing, and forestry","code":"AX"},{"name":"Health and other social services","code":"JX"},{"name":"Industry and trade","code":"YX"}],"mjtheme":["Public sector governance","Environment and natural resources management","Rural development","Human development","Human development"],"themecode":"67,65,78,82,27","mjthemecode":"2,11,10,8,8","mjtheme_namecode":[{"name":"Public sector governance","code":"2"},{"name":"Environment and natural resources management","code":"11"},{"name":"Rural development","code":"10"},{"name":"Human development","code":"8"},{"name":"Human development","code":"8"}],"sector_namecode":[{"name":"General public administration sector","code":"BZ"},{"name":"General education sector","code":"EZ"},{"name":"General agriculture, fishing and forestry sector","code":"AZ"},{"name":"Health","code":"JA"},{"name":"General industry and trade sector","code":"YZ"}],"theme_namecode":[{"name":"Public expenditure, financial management and procurement","code":"27"},{"name":"Environmental policies and institutions","code":"82"},{"name":"Rural services and infrastructure","code":"78"},{"name":"Education for all","code":"65"},{"name":"Health system performance","code":"67"}],"source":"IBRD","majorsector_percent":[{"Name":"Public Administration, Law, and Justice","Percent":43},{"Name":"Education","Percent":28},{"Name":"Agriculture, fishing, and forestry","Percent":13},{"Name":"Health and other social services","Percent":8},{"Name":"Industry and trade","Percent":8}],"projectdocs":[{"DocTypeDesc":"Implementation Completion and Results Report (ICR),  Vol.1","DocType":"ICR","EntityID":"000334955_20080828032513","DocURL":"http://www-wds.worldbank.org/servlet/WDSServlet?pcont=details&eid=000334955_20080828032513","DocDate":"28-JUN-2008"},{"DocTypeDesc":"Implementation Completion and Results Report (ICR),  Vol.1","DocType":"ICR","EntityID":"000160016_20060109110903","DocURL":"http://www-wds.worldbank.org/servlet/WDSServlet?pcont=details&eid=000160016_20060109110903","DocDate":"30-DEC-2005"},{"DocTypeDesc":"Credit Agreement (),  Vol.","DocType":"000014464_2010030110310130","EntityID":"http://www-wds.worldbank.org/servlet/WDSServlet?pcont=details&eid=000014464_2010030110310130","DocURL":"21-JUL-2004"},{"DocTypeDesc":"Credit Agreement (CA),  Vol.","DocType":"CA","EntityID":"000014464_2010030110310130","DocURL":"http://www-wds.worldbank.org/servlet/WDSServlet?pcont=details&eid=000014464_2010030110310130","DocDate":"21-JUL-2004"},{"DocTypeDesc":"Program Document (PGD),  Vol.1","DocType":"PGD","EntityID":"000160016_20040629120930","DocURL":"http://www-wds.worldbank.org/servlet/WDSServlet?pcont=details&eid=000160016_20040629120930","DocDate":"23-JUN-2004"},{"DocTypeDesc":"Program Information Document (PGID),  Vol.1","DocType":"PGID","EntityID":"000012009_20040608132942","DocURL":"http://www-wds.worldbank.org/servlet/WDSServlet?pcont=details&eid=000012009_20040608132942","DocDate":"06-MAY-2004"}],"countryname":"Republic of Madagascar"}},"facets":{}}